odoo9_addon_mrp_disable_force_availability_button-9.0.1.0.0-py2.7-nspkg.pth
odoo9_addon_mrp_disable_force_availability_button-9.0.1.0.0.dist-info/DESCRIPTION.rst
odoo9_addon_mrp_disable_force_availability_button-9.0.1.0.0.dist-info/METADATA
odoo9_addon_mrp_disable_force_availability_button-9.0.1.0.0.dist-info/RECORD
odoo9_addon_mrp_disable_force_availability_button-9.0.1.0.0.dist-info/WHEEL
odoo9_addon_mrp_disable_force_availability_button-9.0.1.0.0.dist-info/metadata.json
odoo9_addon_mrp_disable_force_availability_button-9.0.1.0.0.dist-info/namespace_packages.txt
odoo9_addon_mrp_disable_force_availability_button-9.0.1.0.0.dist-info/top_level.txt
odoo_addons/mrp_disable_force_availability_button/README.rst
odoo_addons/mrp_disable_force_availability_button/__init__.py
odoo_addons/mrp_disable_force_availability_button/__openerp__.py
odoo_addons/mrp_disable_force_availability_button/security/mrp_disable_force_availability_button_security.xml
odoo_addons/mrp_disable_force_availability_button/views/mrp_operation_view.xml
