Metadata-Version: 2.0
Name: odoo9-addon-mrp-disable-force-availability-button
Version: 9.0.1.0.0
Summary: Disable force availability button in manufacturing orders.
Home-page: http://www.odoomrp.com
Author: EficentOdoo Community Association (OCA),
Author-email: support@odoo-community.org
License: AGPL-3
Platform: UNKNOWN
Classifier: Programming Language :: Python :: 2.7
Classifier: Framework :: Odoo
Classifier: License :: OSI Approved :: GNU Affero General Public License v3
Requires-Dist: odoo (<9.1a,>=9.0a)
